Metadata-Version: 2.1
Name: django-regex
Version: 0.4.1
Summary: Fields and utilities to work with regular expression in Django
Home-page: https://github.com/saxix/django-regex
Author: Stefano Apostolico
Author-email: s.apostolico@gmail.com
License: MIT
Platform: linux
Classifier: Environment :: Web Environment
Classifier: Framework :: Django
Classifier: Framework :: Django
Classifier: Framework :: Django :: 1.11
Classifier: Framework :: Django :: 2.0
Classifier: Framework :: Django :: 2.1
Classifier: Operating System :: OS Independent
Classifier: Programming Language :: Python :: 2.7
Classifier: Programming Language :: Python :: 3.6
Classifier: Intended Audience :: Developers
Provides-Extra: tests
Provides-Extra: test
Provides-Extra: extra
Provides-Extra: dev
